MANIFEST.in
setup.cfg
setup.py
SimpleSiteTemplate.egg-info/PKG-INFO
SimpleSiteTemplate.egg-info/SOURCES.txt
SimpleSiteTemplate.egg-info/dependency_links.txt
SimpleSiteTemplate.egg-info/entry_points.txt
SimpleSiteTemplate.egg-info/not-zip-safe
SimpleSiteTemplate.egg-info/requires.txt
SimpleSiteTemplate.egg-info/top_level.txt
simplesitetemplate/__init__.py
simplesitetemplate/template/MANIFEST.in_tmpl
simplesitetemplate/template/README.txt_tmpl
simplesitetemplate/template/development.ini_tmpl
simplesitetemplate/template/ez_setup.py
simplesitetemplate/template/setup.cfg_tmpl
simplesitetemplate/template/setup.py_tmpl
simplesitetemplate/template/test.ini_tmpl
simplesitetemplate/template/+package+/__init__.py
simplesitetemplate/template/+package+/websetup.py_tmpl
simplesitetemplate/template/+package+/config/__init__.py
simplesitetemplate/template/+package+/config/deployment.ini_tmpl_tmpl
simplesitetemplate/template/+package+/config/environment.py_tmpl
simplesitetemplate/template/+package+/config/middleware.py_tmpl
simplesitetemplate/template/+package+/config/routing.py_tmpl
simplesitetemplate/template/+package+/controllers/__init__.py
simplesitetemplate/template/+package+/controllers/account.py_tmpl
simplesitetemplate/template/+package+/controllers/comment.py_tmpl
simplesitetemplate/template/+package+/controllers/error.py_tmpl
simplesitetemplate/template/+package+/controllers/nav.py_tmpl
simplesitetemplate/template/+package+/controllers/page.py_tmpl
simplesitetemplate/template/+package+/controllers/section.py_tmpl
simplesitetemplate/template/+package+/controllers/tag.py_tmpl
simplesitetemplate/template/+package+/lib/__init__.py
simplesitetemplate/template/+package+/lib/app_globals.py
simplesitetemplate/template/+package+/lib/auth.py
simplesitetemplate/template/+package+/lib/base.py_tmpl
simplesitetemplate/template/+package+/lib/helpers.py_tmpl
simplesitetemplate/template/+package+/lib/middleware.py
simplesitetemplate/template/+package+/model/__init__.py_tmpl
simplesitetemplate/template/+package+/model/meta.py
simplesitetemplate/template/+package+/public/css/main.css
simplesitetemplate/template/+package+/public/yui/2.6.0/LICENSE.txt_tmpl
simplesitetemplate/template/+package+/public/yui/2.6.0/animation/animation-min.js
