Metadata-Version: 1.0
Name: SimpleSiteTemplate
Version: 0.1
Summary: A Paste Template which allows you to create a new Pylons project based on the SimpleSite tutorial described in the Pylons Book
Home-page: http://pylonsbook.com
Author: James Gardner
Author-email: feeback@pylonsbook.com
License: BSD, see the simplesitetemplate/template/+pacakge+/public/yui/2.6.0/LICENSE.txt_tmpl file for details.
Keywords: Pylons Paste Template SimpleSite Simple Site Website
Platform: UNKNOWN
